ptee/__init__.py
ptee/instance.py
ptee/run.py
cqh_ptee-0.0.1.dist-info/METADATA
cqh_ptee-0.0.1.dist-info/WHEEL
cqh_ptee-0.0.1.dist-info/entry_points.txt
cqh_ptee-0.0.1.dist-info/top_level.txt
cqh_ptee-0.0.1.dist-info/RECORD
